mistune_telegram_plugin/__init__.py
mistune_telegram_plugin/renderers.py
mistune_telegram_plugin-0.1.0.dist-info/METADATA
mistune_telegram_plugin-0.1.0.dist-info/WHEEL
mistune_telegram_plugin-0.1.0.dist-info/RECORD
